HISTORY.rst
docs/Makefile
docs/source/_static/custom.css
docs/source/api.rst
docs/source/conf.py
docs/source/extract.rst
docs/source/history.rst
docs/source/index.rst
docs/source/low-level.rst
docs/source/overview.rst
docs/source/preprocess.rst
piculet.py
tests/conftest.py
tests/test_cli.py
tests/test_extract.py
tests/test_html.py
tests/test_preprocess.py
tests/test_reducers.py
tests/test_scrape.py
tests/test_xpath.py
piculet-1.0.1.dist-info/entry_points.txt
piculet-1.0.1.dist-info/LICENSE.txt
piculet-1.0.1.dist-info/WHEEL
piculet-1.0.1.dist-info/METADATA
piculet-1.0.1.dist-info/RECORD
